LICENSE
README.md
pyproject.toml
setup.py
candyfloss/__init__.py
candyfloss/core.py
candyfloss/utils.py
candyfloss.egg-info/PKG-INFO
candyfloss.egg-info/SOURCES.txt
candyfloss.egg-info/dependency_links.txt
candyfloss.egg-info/requires.txt
candyfloss.egg-info/top_level.txt
native/py_entrypoint.c