Metadata-Version: 2.4
Name: candyfloss
Version: 0.0.2
Summary: An ergonomic interface over GStreamer
Author-email: Bob Poekert <bob@poekert.com>
License-Expression: MIT
Project-URL: Homepage, https://git.hella.cheap/bob/candyfloss
Classifier: Programming Language :: Python :: 3
Requires-Python: >=3.11
License-File: LICENSE
Requires-Dist: Pillow
Dynamic: license-file
